milwrap/__init__.py
milwrap/__version__.py
milwrap/countbase.py
milwrap-0.2.0.dist-info/LICENSE
milwrap-0.2.0.dist-info/METADATA
milwrap-0.2.0.dist-info/WHEEL
milwrap-0.2.0.dist-info/RECORD
