Metadata-Version: 2.3
Name: milwrap
Version: 0.2.0
Summary: milwrap - multiple instane meta-learner that can use any supervised-learning algorithms.
License: MIT
Keywords: machine learning
Author: Akimitsu Inoue
Author-email: akimitsu.inoue@gmail.com
Requires-Python: >=3.10
Classifier: Development Status :: 4 - Beta
Classifier: Intended Audience :: Developers
Classifier: License :: OSI Approved :: MIT License
Classifier: Programming Language :: Python :: 3
Classifier: Programming Language :: Python :: 3.10
Classifier: Programming Language :: Python :: 3.11
Classifier: Programming Language :: Python :: 3.12
Classifier: Programming Language :: Python :: 3.13
Requires-Dist: numpy (>=1.22.0)
Requires-Dist: pandas (>=1.3.0)
Requires-Dist: scikit-learn (>=1.0.0)
Project-URL: Homepage, https://github.com/inoueakimitsu/milwrap
Project-URL: Repository, https://github.com/inoueakimitsu/milwrap
